catzilla-0.2.0.dist-info/RECORD
catzilla-0.2.0.dist-info/LICENSE
catzilla-0.2.0.dist-info/WHEEL
catzilla-0.2.0.dist-info/entry_points.txt
catzilla-0.2.0.dist-info/top_level.txt
catzilla-0.2.0.dist-info/METADATA
catzilla/dependency_injection.py
catzilla/logging.py
catzilla/background_tasks.py
catzilla/memory_c.py
catzilla/streaming.py.new
catzilla/startup_banner.py
catzilla/memory.py
catzilla/async_detector.py
catzilla/_catzilla.cpython-312-darwin.so
catzilla/__init__.py
catzilla/response.py
catzilla/cache_middleware.py
catzilla/types.py
catzilla/factory.py
catzilla/dev_logger.py
catzilla/integration.py
catzilla/hybrid_executor.py
catzilla/app.py
catzilla/exceptions.py
catzilla/uploads.py
catzilla/router.py
catzilla/streaming.py
catzilla/smart_cache.py
catzilla/auto_validation.py
catzilla/scope.py
catzilla/middleware.py
catzilla/validation.py
catzilla/decorators.py
catzilla/ui/collectors.py
catzilla/ui/formatters.py
catzilla/ui/__init__.py
catzilla/ui/dev_logger.py
catzilla/ui/banner.py
catzilla/logging/formatters.py
catzilla/logging/__init__.py
catzilla/logging/dev_logger.py
catzilla/logging/banner.py
