Metadata-Version: 2.4
Name: catzilla
Version: 0.2.0
Summary: Ultra-fast Python web framework with C-accelerated routing
Author-email: Rezwan Ahmed Sami <samiahmed0f0@gmail.com>
Maintainer-email: Rezwan Ahmed Sami <samiahmed0f0@gmail.com>
License: MIT
Project-URL: Homepage, https://github.com/rezwanahmedsami/catzilla
Project-URL: Documentation, https://catzilla.rezwanahmedsami.com/
Project-URL: Repository, https://github.com/rezwanahmedsami/catzilla
Project-URL: Bug Tracker, https://github.com/rezwanahmedsami/catzilla/issues
Project-URL: Source Code, https://github.com/rezwanahmedsami/catzilla
Project-URL: Changelog, https://github.com/rezwanahmedsami/catzilla/blob/main/CHANGELOG.md
Project-URL: Performance Report, https://github.com/rezwanahmedsami/catzilla/blob/main/PERFORMANCE_REPORT_v0.1.0.md
Keywords: web-framework,fast,performance,c-extension,routing,http,asgi,web-server,high-performance,micro-framework
Classifier: Development Status :: 4 - Beta
Classifier: Intended Audience :: Developers
Classifier: Programming Language :: Python :: 3
Classifier: Programming Language :: Python :: 3.9
Classifier: Programming Language :: Python :: 3.10
Classifier: Programming Language :: Python :: 3.11
Classifier: Programming Language :: Python :: 3.12
Classifier: Programming Language :: Python :: 3.13
Classifier: Programming Language :: C
Classifier: Topic :: Internet :: WWW/HTTP :: HTTP Servers
Classifier: Topic :: Internet :: WWW/HTTP :: Dynamic Content
Classifier: Topic :: Software Development :: Libraries :: Python Modules
Classifier: Topic :: Software Development :: Libraries :: Application Frameworks
Classifier: Operating System :: OS Independent
Classifier: Operating System :: POSIX :: Linux
Classifier: Operating System :: Microsoft :: Windows
Classifier: Operating System :: MacOS
Classifier: Environment :: Web Environment
Classifier: Framework :: AsyncIO
Classifier: Typing :: Typed
Requires-Python: >=3.9
License-File: LICENSE
Requires-Dist: psutil>=5.9.0
Provides-Extra: dev
Requires-Dist: pytest>=7.0.0; extra == "dev"
Requires-Dist: pytest-cov>=4.0.0; extra == "dev"
Requires-Dist: pre-commit>=2.20.0; extra == "dev"
Requires-Dist: black>=22.0.0; extra == "dev"
Requires-Dist: flake8>=5.0.0; extra == "dev"
Requires-Dist: mypy>=1.0.0; extra == "dev"
Requires-Dist: build>=0.10.0; extra == "dev"
Requires-Dist: twine>=4.0.0; extra == "dev"
Provides-Extra: benchmarks
Requires-Dist: fastapi>=0.100.0; extra == "benchmarks"
Requires-Dist: uvicorn>=0.24.0; extra == "benchmarks"
Requires-Dist: flask>=2.3.0; extra == "benchmarks"
Requires-Dist: django>=4.2.0; extra == "benchmarks"
Requires-Dist: gunicorn>=21.2.0; extra == "benchmarks"
Requires-Dist: matplotlib>=3.7.0; extra == "benchmarks"
Requires-Dist: pandas>=2.0.0; extra == "benchmarks"
Requires-Dist: seaborn>=3.12.0; extra == "benchmarks"
Requires-Dist: numpy>=1.24.0; extra == "benchmarks"
Requires-Dist: requests>=2.31.0; extra == "benchmarks"
Requires-Dist: pillow>=10.0.0; extra == "benchmarks"
Requires-Dist: kiwisolver>=1.4.0; extra == "benchmarks"
Provides-Extra: docs
Requires-Dist: sphinx>=7.0.0; extra == "docs"
Requires-Dist: sphinx-rtd-theme>=2.0.0; extra == "docs"
Requires-Dist: myst-parser>=2.0.0; extra == "docs"
Requires-Dist: sphinx-autodoc-typehints>=1.20.0; extra == "docs"
Provides-Extra: test
Requires-Dist: pytest>=7.0.0; extra == "test"
Requires-Dist: pytest-cov>=4.0.0; extra == "test"
Requires-Dist: pytest-benchmark>=4.0.0; extra == "test"
Requires-Dist: pytest-asyncio>=0.23.0; extra == "test"
Requires-Dist: requests>=2.31.0; extra == "test"
Dynamic: license-file
Dynamic: requires-python
